apache_superset_core-0.0.1rc2.dist-info/licenses/LICENSE.txt
superset_core/__init__.py
superset_core/api/__init__.py
superset_core/api/types/__init__.py
superset_core/api/types/models.py
superset_core/api/types/query.py
superset_core/api/types/rest_api.py
superset_core/extensions/__init__.py
superset_core/extensions/types.py
apache_superset_core-0.0.1rc2.dist-info/METADATA
apache_superset_core-0.0.1rc2.dist-info/WHEEL
apache_superset_core-0.0.1rc2.dist-info/top_level.txt
apache_superset_core-0.0.1rc2.dist-info/RECORD
