Metadata-Version: 2.4
Name: apache-superset-core
Version: 0.0.1rc2
Summary: Core Python package for building Apache Superset backend extensions and integrations
Author-email: Apache Software Foundation <dev@superset.apache.org>
License:                               Apache License
Project-URL: Homepage, https://superset.apache.org/
Project-URL: Documentation, https://superset.apache.org/docs/
Project-URL: Repository, https://github.com/apache/superset
Project-URL: Bug Tracker, https://github.com/apache/superset/issues
Project-URL: Changelog, https://github.com/apache/superset/blob/master/CHANGELOG.md
Keywords: superset,apache,analytics,business-intelligence,extensions,visualization
Classifier: Development Status :: 3 - Alpha
Classifier: Environment :: Web Environment
Classifier: Intended Audience :: Developers
Classifier: License :: OSI Approved :: Apache Software License
Classifier: Operating System :: OS Independent
Classifier: Programming Language :: Python :: 3
Classifier: Programming Language :: Python :: 3.10
Classifier: Programming Language :: Python :: 3.11
Classifier: Programming Language :: Python :: 3.12
Classifier: Topic :: Database
Classifier: Topic :: Scientific/Engineering :: Visualization
Classifier: Topic :: Software Development :: Libraries :: Python Modules
Requires-Python: >=3.10
License-File: LICENSE.txt
Requires-Dist: flask-appbuilder<5.0.0,>=4.5.3
Dynamic: license-file
